oikan/__init__.py
oikan/elasticnet.py
oikan/exceptions.py
oikan/model.py
oikan/neural.py
oikan/utils.py
oikan-0.0.3.12.dist-info/licenses/LICENSE
oikan-0.0.3.12.dist-info/METADATA
oikan-0.0.3.12.dist-info/WHEEL
oikan-0.0.3.12.dist-info/top_level.txt
oikan-0.0.3.12.dist-info/RECORD
