Metadata-Version: 2.4
Name: oikan
Version: 0.0.3.12
Summary: OIKAN: Neuro-Symbolic ML for Scientific Discovery
Author: Arman Zhalgasbayev
License: MIT
Project-URL: Homepage, https://github.com/silvermete0r/oikan
Project-URL: Bug Tracker, https://github.com/silvermete0r/oikan/issues
Classifier: Programming Language :: Python :: 3
Classifier: License :: OSI Approved :: MIT License
Classifier: Operating System :: OS Independent
Requires-Python: >=3.11
License-File: LICENSE
Requires-Dist: torch
Requires-Dist: numpy
Requires-Dist: scikit-learn
Requires-Dist: tqdm
Requires-Dist: sympy
Dynamic: license-file
